receipt_statement_linker/__init__.py
receipt_statement_linker/categorize.py
receipt_statement_linker/config.py
receipt_statement_linker/extract.py
receipt_statement_linker/main.py
receipt_statement_linker/pair.py
receipt_statement_linker/receipt.py
receipt_statement_linker/statement.py
receipt_statement_linker-0.2.0.dist-info/METADATA
receipt_statement_linker-0.2.0.dist-info/WHEEL
receipt_statement_linker-0.2.0.dist-info/entry_points.txt
receipt_statement_linker-0.2.0.dist-info/licenses/LICENSE
receipt_statement_linker-0.2.0.dist-info/RECORD
