Metadata-Version: 2.4
Name: receipt-statement-linker
Version: 0.2.0
Summary: Link receipts to bank statement transactions
License-File: LICENSE
Classifier: Development Status :: 3 - Alpha
Classifier: Intended Audience :: Developers
Classifier: License :: OSI Approved :: GNU General Public License v3 (GPLv3)
Classifier: Operating System :: OS Independent
Classifier: Programming Language :: Python :: 3
Classifier: Topic :: Utilities
Requires-Python: >=3.12
Requires-Dist: litellm>=1.66.0
Requires-Dist: typer>=0.15.2
